nltrace/__init__.py
nltrace/skeleton.py
nltrace-0.1.0.dist-info/LICENSE.txt
nltrace-0.1.0.dist-info/METADATA
nltrace-0.1.0.dist-info/WHEEL
nltrace-0.1.0.dist-info/top_level.txt
nltrace-0.1.0.dist-info/RECORD
