Metadata-Version: 2.1
Name: nltrace
Version: 0.1.0
Summary: Add a short description here!
Home-page: https://nltrace.org
Author: Christian Krieg
Author-email: christian@nltrace.org
License: Proprietary
Project-URL: Documentation, https://nltrace.org/
Project-URL: Source, https://github.com/nltrace/nltrace/
Project-URL: Twitter, https://twitter.com/nltrace_io
Platform: any
Classifier: Development Status :: 4 - Beta
Classifier: Programming Language :: Python
Requires-Python: >=3.8
License-File: LICENSE.txt
Requires-Dist: importlib-metadata ; python_version < "3.8"
Provides-Extra: testing
Requires-Dist: setuptools ; extra == 'testing'
Requires-Dist: pytest ; extra == 'testing'
Requires-Dist: pytest-cov ; extra == 'testing'
